{
  "typename": "User",
  "affiliatesHighlightedLabel": {
    "label": {
      "url": {
        "url": "https://twitter.com/openmind_agi",
        "urlType": "DeepLink"
      },
      "badge": {
        "url": "https://pbs.twimg.com/profile_images/1960774381938073602/pVvCc-HA_bigger.jpg"
      },
      "description": "OpenMind",
      "userLabelType": "BusinessLabel",
      "userLabelDisplayType": "Badge"
    }
  },
  "hasGraduatedAccess": true,
  "id": "VXNlcjoxNTM3MjQ4NTQwNjQwMjk2OTYw",
  "isBlueVerified": true,
  "legacy": {
    "canDm": true,
    "canMediaTag": true,
    "createdAt": "Thu Jun 16 01:40:02 +0000 2022",
    "defaultProfile": true,
    "defaultProfileImage": false,
    "description": "Vibing @openmind_agi @FindYourEdgePod | Crypto + AI + Robotics | Rebel @0xUClub @HKUniversity @ucl @PKU1898 | Gymrat | Ego 👇 Agency 👆",
    "entities": {
      "description": {
        "urls": []
      }
    },
    "fastFollowersCount": 0,
    "favouritesCount": 7114,
    "followersCount": 5009,
    "following": true,
    "friendsCount": 3531,
    "hasCustomTimelines": true,
    "isTranslator": false,
    "listedCount": 64,
    "location": "Onchain",
    "mediaCount": 637,
    "name": "ClaraCheng.eth ➡️ Breakpoint 🇦🇪",
    "normalFollowersCount": 5009,
    "pinnedTweetIdsStr": [
      "1968527515183628783"
    ],
    "possiblySensitive": false,
    "profileBannerUrl": "https://pbs.twimg.com/profile_banners/1537248540640296960/1756053125",
    "profileImageUrlHttps": "https://pbs.twimg.com/profile_images/1959652030534074368/tbiQKJGs_normal.jpg",
    "profileInterstitialType": "",
    "screenName": "ClaraChengGo",
    "statusesCount": 4343,
    "translatorType": "none",
    "verified": false,
    "wantRetweets": true,
    "withheldInCountries": []
  },
  "profileImageShape": "Circle",
  "restId": "1537248540640296960",
  "tipjarSettings": {}
}