{
  "typename": "User",
  "affiliatesHighlightedLabel": {},
  "hasGraduatedAccess": true,
  "id": "VXNlcjoxNDI2MDk2MA==",
  "isBlueVerified": true,
  "legacy": {
    "canDm": false,
    "canMediaTag": true,
    "createdAt": "Sun Mar 30 21:04:14 +0000 2008",
    "defaultProfile": false,
    "defaultProfileImage": false,
    "description": "Father, former Prime Minister of Canada. | Papa, ancien premier ministre du Canada.",
    "entities": {
      "description": {
        "urls": []
      },
      "url": {
        "urls": [
          {
            "display_url": "youtube.com/@JustinTrudeau",
            "expanded_url": "http://www.youtube.com/@JustinTrudeau",
            "url": "https://t.co/uXcYXUr0Pc",
            "indices": [
              0,
              23
            ]
          }
        ]
      }
    },
    "fastFollowersCount": 0,
    "favouritesCount": 218,
    "followersCount": 6429994,
    "following": true,
    "friendsCount": 877,
    "hasCustomTimelines": true,
    "isTranslator": false,
    "listedCount": 15952,
    "location": "",
    "mediaCount": 11968,
    "name": "Justin Trudeau",
    "normalFollowersCount": 6429994,
    "pinnedTweetIdsStr": [
      "1892793839649272278"
    ],
    "possiblySensitive": false,
    "profileBannerUrl": "https://pbs.twimg.com/profile_banners/14260960/1629043620",
    "profileImageUrlHttps": "https://pbs.twimg.com/profile_images/1426938479909421056/QpI3TSNn_normal.jpg",
    "profileInterstitialType": "",
    "screenName": "JustinTrudeau",
    "statusesCount": 48974,
    "translatorType": "none",
    "url": "https://t.co/uXcYXUr0Pc",
    "verified": false,
    "verifiedType": "Government",
    "wantRetweets": true,
    "withheldInCountries": []
  },
  "profileImageShape": "Circle",
  "restId": "14260960",
  "tipjarSettings": {}
}